datasette_plot/__init__.py
datasette_plot/static/main.min.css
datasette_plot/static/main.min.js
datasette_plot-0.1.0.dist-info/LICENSE
datasette_plot-0.1.0.dist-info/METADATA
datasette_plot-0.1.0.dist-info/WHEEL
datasette_plot-0.1.0.dist-info/entry_points.txt
datasette_plot-0.1.0.dist-info/top_level.txt
datasette_plot-0.1.0.dist-info/RECORD
