Metadata-Version: 2.1
Name: datasette-plot
Version: 0.1.0
Summary: Observable Plot Datasette plugin
Author: Alex Garcia
License: Apache-2.0
Project-URL: Homepage, https://github.com/datasette/datasette-plot
Project-URL: Changelog, https://github.com/datasette/datasette-plot/releases
Project-URL: Issues, https://github.com/datasette/datasette-plot/issues
Project-URL: CI, https://github.com/datasette/datasette-plot/actions
Classifier: Framework :: Datasette
Classifier: License :: OSI Approved :: Apache Software License
Requires-Python: >=3.8
License-File: LICENSE
Requires-Dist: datasette >=1.0a6
Provides-Extra: test
Requires-Dist: pytest ; extra == 'test'
Requires-Dist: pytest-asyncio ; extra == 'test'
Requires-Dist: ruff ; extra == 'test'
